egsis/.ipynb_checkpoints/model-checkpoint.py
egsis/__init__.py
egsis/annotators/__init__.py
egsis/annotators/point_annotator.py
egsis/complex_networks.py
egsis/datasets/__init__.py
egsis/datasets/grabcut.py
egsis/features.py
egsis/gabor.py
egsis/image.py
egsis/labeling.py
egsis/lcu.py
egsis/main.py
egsis/metrics.py
egsis/model.py
egsis/superpixels.py
egsis-0.1.0.dist-info/WHEEL
egsis-0.1.0.dist-info/METADATA
egsis-0.1.0.dist-info/licenses/LICENSE
egsis-0.1.0.dist-info/RECORD
