Metadata-Version: 2.1
Name: egsis
Version: 0.1.0
Summary: Exploratory Graph-based Semi-Supervised Image Segmentation
License: MIT
Author-email: Manoel Vilela <manoel_vilela@engineer.com>
Requires-Python: >=3.9,<3.12
Requires-Dist: ipycanvas>=0.13.1
Requires-Dist: loguru>=0.6.0
Requires-Dist: matplotlib>=3.7.1
Requires-Dist: networkx>=2.8.6
Requires-Dist: scikit-image>=0.21.0rc0
Requires-Dist: scipy>=1.10.1
Requires-Dist: typer>=0.6.1
